readme.rst
vitae/__init__.py
vitae/vitae.py
vitae/data/bibs.bib
vitae-1.1.3.dist-info/LICENSE
vitae-1.1.3.dist-info/METADATA
vitae-1.1.3.dist-info/WHEEL
vitae-1.1.3.dist-info/top_level.txt
vitae-1.1.3.dist-info/RECORD
