Metadata-Version: 2.1
Name: vitae
Version: 1.1.3
Summary: Tools for academics for building a Curriculum Vitae and other oft-requested documents.
Home-page: https://github.com/josephcslater/vitae
Author: Joseph C. Slater
Author-email: joseph.c.slater@gmail.com
License: UNKNOWN
Keywords: curriculum vitae,academia,cv,resume
Platform: UNKNOWN
Requires-Dist: bibtexparser
Requires-Dist: appdirs
